pipilgrim/__init__.py
pipilgrim/__main__.py
pipilgrim/file_resource.py
pipilgrim/instance_provider.py
pipilgrim/pilgrim_assembly.py
pi_pilgrim-0.1.3.dist-info/LICENSE
pi_pilgrim-0.1.3.dist-info/METADATA
pi_pilgrim-0.1.3.dist-info/WHEEL
pi_pilgrim-0.1.3.dist-info/RECORD
