Metadata-Version: 2.1
Name: pi-pilgrim
Version: 0.1.3
Summary: 
Author: Jasper Blues
Author-email: jasper@liberation-data.com
Requires-Python: >=3.11,<4.0
Classifier: Programming Language :: Python :: 3
Classifier: Programming Language :: Python :: 3.11
Classifier: Programming Language :: Python :: 3.12
Requires-Dist: loguru (>=0.7.2,<0.8.0)
Requires-Dist: python-dotenv (>=1.0.1,<2.0.0)
